ediff/__init__.py
ediff/__main__.py
ediff/bkg.py
ediff/bkg2d.py
ediff/calibration.py
ediff/center.py
ediff/gcryst.py
ediff/io.py
ediff/mcryst.py
ediff/pcryst.py
ediff/radial.py
ediff-1.0.dist-info/licenses/LICENCE
ediff-1.0.dist-info/METADATA
ediff-1.0.dist-info/WHEEL
ediff-1.0.dist-info/top_level.txt
ediff-1.0.dist-info/RECORD
